salsa/SaLSA.py
salsa/__init__.py
salsa/adam_sls.py
salsa/sls_base.py
SaLSa_Optimizer-0.1.0.dist-info/LICENSE
SaLSa_Optimizer-0.1.0.dist-info/METADATA
SaLSa_Optimizer-0.1.0.dist-info/WHEEL
SaLSa_Optimizer-0.1.0.dist-info/top_level.txt
SaLSa_Optimizer-0.1.0.dist-info/RECORD
