Metadata-Version: 2.1
Name: SaLSa-Optimizer
Version: 0.1.0
Summary: A pytorch optimizer that does not need a learning rate
Author-email: Philip Kenneweg <pkenneweg@techfak.uni-bielefeld.de>
License: MIT
Project-URL: Homepage, https://github.com/TheMody/No-learning-rates-needed-Introducing-SALSA-Stable-Armijo-Line-Search-Adaptation
Project-URL: Documentation, https://github.com/TheMody/No-learning-rates-needed-Introducing-SALSA-Stable-Armijo-Line-Search-Adaptation/wiki
Project-URL: Tracker, https://github.com/TheMody/No-learning-rates-needed-Introducing-SALSA-Stable-Armijo-Line-Search-Adaptation/issues
Classifier: Programming Language :: Python :: 3
Classifier: License :: OSI Approved :: MIT License
Classifier: Operating System :: OS Independent
Requires-Python: >=3.6
License-File: LICENSE
Requires-Dist: torch
Requires-Dist: numpy
